{"symbols": {"O": ["DEDEKIND_CUTS", "REAL+", "DEDEKIND_CUT", "GLUED", "one", "lcm", "hcf", "RED", "RAT+", "numerator", "denominator", "/", "quotient", "+", "*'", "0", "card", "nextcard", "aleph", "Segm", "NAT", "REAL", "COMPLEX", "RAT", "INT", "ExtREAL", "[#]", "`", "choose", "<i>", "+infty", "-infty", "min", "max", "IFGT", "bool"], "R": ["are_coprime", "divides", "<='", "<", "<>", "in", "<=", ">=", ">", "are_mutually_distinct"], "V": ["cardinal", "limit_cardinal", "-element", "strict", "proper", "complex", "zero", "ext-real", "positive", "negative", "trivial"], "M": ["Cardinal", "object", "Real", "Element", "Subset", "Complex", "ExtReal"], "K": ["[:"], "L": [":]"]}, "contents": [[["begin", "begin"]], [["reserve", "reserve"], ["x", "__variable_"], [",", ","], ["y", "__variable_"], [",", ","], ["z", "__variable_"], ["for", "for"], ["Real", "__M_"], [";", ";"]], [["Lm1", "__label_"], [":", ":"], ["x", "__variable_"], ["<=", "__R_"], ["y", "__variable_"], ["&", "&"], ["y", "__variable_"], ["<=", "__R_"], ["x", "__variable_"], ["implies", "implies"], ["x", "__variable_"], ["=", "="], ["y", "__variable_"]], [["proof", "proof"]], [["assume", "assume"], ["that", "that"]], [["A1", "__label_"], [":", ":"], ["x", "__variable_"], ["<=", "__R_"], ["y", "__variable_"], ["and", "and"]], [["A2", "__label_"], [":", ":"], ["y", "__variable_"], ["<=", "__R_"], ["x", "__variable_"], [";", ";"]], [["A3", "__label_"], [":", ":"], ["x", "__variable_"], ["in", "__R_"], ["REAL", "__O255_"], ["&", "&"], ["y", "__variable_"], ["in", "__R_"], ["REAL", "__O255_"], ["by", "by"], ["XREAL_0", "__label_"], [":", ":"], ["def", "def"], ["1", "__number_"], [";", ";"]], [["per", "per"], ["cases", "cases"], ["by", "by"], ["A3", "__label_"], [",", ","], ["NUMBERS", "__label_"], [":", ":"], ["def", "def"], ["1", "__number_"], [",", ","], ["XBOOLE_0", "__label_"], [":", ":"], ["def", "def"], ["3", "__number_"], [";", ";"]], [["suppose", "suppose"]], [["x", "__variable_"], ["in", "__R_"], ["REAL+", "__O_"], ["&", "&"], ["y", "__variable_"], ["in", "__R_"], ["REAL+", "__O_"], [";", ";"]], [["then", "then"]], [["(", "("], ["ex", "ex"], ["x9", "__variable_"], [",", ","], ["y9", "__variable_"], ["being", "being"], ["Element", "__M_"], ["of", "of"], ["REAL+", "__O_"], ["st", "st"], ["x", "__variable_"], ["=", "="], ["x9", "__variable_"], ["&", "&"], ["y", "__variable_"], ["=", "="], ["y9", "__variable_"], ["&", "&"], ["x9", "__variable_"], ["<='", "__R_"], ["y9", "__variable_"], [")", ")"], ["&", "&"], ["ex", "ex"]], [["y99", "__variable_"], [",", ","], ["x99", "__variable_"], ["being", "being"], ["Element", "__M_"], ["of", "of"], ["REAL+", "__O_"], ["st", "st"], ["y", "__variable_"], ["=", "="], ["y99", "__variable_"], ["&", "&"], ["x", "__variable_"], ["=", "="], ["x99", "__variable_"], ["&", "&"], ["y99", "__variable_"], ["<='", "__R_"], ["x99", "__variable_"], ["by", "by"], ["A1", "__label_"], [",", ","], ["A2", "__label_"], [",", ","]], [["XXREAL_0", "__label_"], [":", ":"], ["def", "def"], ["5", "__number_"], [";", ";"]], [["hence", "hence"], ["thesis", "thesis"], ["by", "by"], ["ARYTM_1", "__label_"], [":", ":"], ["4", "__number_"], [";", ";"]], [["end", "end"], [";", ";"]], [["suppose", "suppose"]], [["A4", "__label_"], [":", ":"], ["x", "__variable_"], ["in", "__R_"], ["REAL+", "__O_"], ["&", "&"], ["y", "__variable_"], ["in", "__R_"], ["[:", "__K_"], ["{", "{"], ["0", "__O_"], ["}", "}"], [",", ","], ["REAL+", "__O_"], [":]", "__L_"], [";", ";"]], [["then", "then"]], [["(", "("], ["not", "not"], ["(", "("], ["x", "__variable_"], ["in", "__R_"], ["REAL+", "__O_"], ["&", "&"], ["y", "__variable_"], ["in", "__R_"], ["REAL+", "__O_"], [")", ")"], [")", ")"], ["&", "&"], ["not", "not"], ["(", "("], ["x", "__variable_"], ["in", "__R_"], ["[:", "__K_"], ["{", "{"], ["0", "__O_"], ["}", "}"], [",", ","], ["REAL+", "__O_"], [":]", "__L_"], ["&", "&"], ["y", "__variable_"], ["in", "__R_"], ["[:", "__K_"], ["{", "{"], ["0", "__O_"], ["}", "}"], [",", ","]], [["REAL+", "__O_"], [":]", "__L_"], [")", ")"], ["by", "by"], ["ARYTM_0", "__label_"], [":", ":"], ["5", "__number_"], [",", ","], ["XBOOLE_0", "__label_"], [":", ":"], ["3", "__number_"], [";", ";"]], [["hence", "hence"], ["thesis", "thesis"], ["by", "by"], ["A1", "__label_"], [",", ","], ["A4", "__label_"], [",", ","], ["XXREAL_0", "__label_"], [":", ":"], ["def", "def"], ["5", "__number_"], [";", ";"]], [["end", "end"], [";", ";"]], [["suppose", "suppose"]], [["A5", "__label_"], [":", ":"], ["y", "__variable_"], ["in", "__R_"], ["REAL+", "__O_"], ["&", "&"], ["x", "__variable_"], ["in", "__R_"], ["[:", "__K_"], ["{", "{"], ["0", "__O_"], ["}", "}"], [",", ","], ["REAL+", "__O_"], [":]", "__L_"], [";", ";"]], [["then", "then"]], [["(", "("], ["not", "not"], ["(", "("], ["x", "__variable_"], ["in", "__R_"], ["REAL+", "__O_"], ["&", "&"], ["y", "__variable_"], ["in", "__R_"], ["REAL+", "__O_"], [")", ")"], [")", ")"], ["&", "&"], ["not", "not"], ["(", "("], ["x", "__variable_"], ["in", "__R_"], ["[:", "__K_"], ["{", "{"], ["0", "__O_"], ["}", "}"], [",", ","], ["REAL+", "__O_"], [":]", "__L_"], ["&", "&"], ["y", "__variable_"], ["in", "__R_"], ["[:", "__K_"], ["{", "{"], ["0", "__O_"], ["}", "}"], [",", ","]], [["REAL+", "__O_"], [":]", "__L_"], [")", ")"], ["by", "by"], ["ARYTM_0", "__label_"], [":", ":"], ["5", "__number_"], [",", ","], ["XBOOLE_0", "__label_"], [":", ":"], ["3", "__number_"], [";", ";"]], [["hence", "hence"], ["thesis", "thesis"], ["by", "by"], ["A2", "__label_"], [",", ","], ["A5", "__label_"], [",", ","], ["XXREAL_0", "__label_"], [":", ":"], ["def", "def"], ["5", "__number_"], [";", ";"]], [["end", "end"], [";", ";"]], [["suppose", "suppose"], ["that", "that"]], [["A6", "__label_"], [":", ":"], ["x", "__variable_"], ["in", "__R_"], ["[:", "__K_"], ["{", "{"], ["0", "__O_"], ["}", "}"], [",", ","], ["REAL+", "__O_"], [":]", "__L_"], ["&", "&"], ["y", "__variable_"], ["in", "__R_"], ["[:", "__K_"], ["{", "{"], ["0", "__O_"], ["}", "}"], [",", ","], ["REAL+", "__O_"], [":]", "__L_"], [";", ";"]], [["consider", "consider"], ["x9", "__variable_"], [",", ","], ["y9", "__variable_"], ["being", "being"], ["Element", "__M_"], ["of", "of"], ["REAL+", "__O_"], ["such", "such"], ["that", "that"]], [["A7", "__label_"], [":", ":"], ["x", "__variable_"], ["=", "="], ["[", "["], ["0", "__O_"], [",", ","], ["x9", "__variable_"], ["]", "]"], ["&", "&"], ["y", "__variable_"], ["=", "="], ["[", "["], ["0", "__O_"], [",", ","], ["y9", "__variable_"], ["]", "]"], ["and", "and"]], [["A8", "__label_"], [":", ":"], ["y9", "__variable_"], ["<='", "__R_"], ["x9", "__variable_"], ["by", "by"], ["A1", "__label_"], [",", ","], ["A6", "__label_"], [",", ","], ["XXREAL_0", "__label_"], [":", ":"], ["def", "def"], ["5", "__number_"], [";", ";"]], [["consider", "consider"], ["y99", "__variable_"], [",", ","], ["x99", "__variable_"], ["being", "being"], ["Element", "__M_"], ["of", "of"], ["REAL+", "__O_"], ["such", "such"], ["that", "that"]], [["A9", "__label_"], [":", ":"], ["y", "__variable_"], ["=", "="], ["[", "["], ["0", "__O_"], [",", ","], ["y99", "__variable_"], ["]", "]"], ["&", "&"], ["x", "__variable_"], ["=", "="], ["[", "["], ["0", "__O_"], [",", ","], ["x99", "__variable_"], ["]", "]"], ["and", "and"]], [["A10", "__label_"], [":", ":"], ["x99", "__variable_"], ["<='", "__R_"], ["y99", "__variable_"], ["by", "by"], ["A2", "__label_"], [",", ","], ["A6", "__label_"], [",", ","], ["XXREAL_0", "__label_"], [":", ":"], ["def", "def"], ["5", "__number_"], [";", ";"]], [["x9", "__variable_"], ["=", "="], ["x99", "__variable_"], ["&", "&"], ["y9", "__variable_"], ["=", "="], ["y99", "__variable_"], ["by", "by"], ["A7", "__label_"], [",", ","], ["A9", "__label_"], [",", ","], ["XTUPLE_0", "__label_"], [":", ":"], ["1", "__number_"], [";", ";"]], [["hence", "hence"], ["thesis", "thesis"], ["by", "by"], ["A8", "__label_"], [",", ","], ["A9", "__label_"], [",", ","], ["A10", "__label_"], [",", ","], ["ARYTM_1", "__label_"], [":", ":"], ["4", "__number_"], [";", ";"]], [["end", "end"], [";", ";"]], [["end", "end"], [";", ";"]], [["Lm2", "__label_"], [":", ":"], ["x", "__variable_"], ["<=", "__R_"], ["y", "__variable_"], ["&", "&"], ["y", "__variable_"], ["<=", "__R_"], ["z", "__variable_"], ["implies", "implies"], ["x", "__variable_"], ["<=", "__R_"], ["z", "__variable_"]], [["proof", "proof"]], [["assume", "assume"], ["that", "that"]], [["A1", "__label_"], [":", ":"], ["x", "__variable_"], ["<=", "__R_"], ["y", "__variable_"], ["and", "and"]], [["A2", "__label_"], [":", ":"], ["y", "__variable_"], ["<=", "__R_"], ["z", "__variable_"], [";", ";"]], [["A3", "__label_"], [":", ":"], ["x", "__variable_"], ["in", "__R_"], ["REAL", "__O255_"], ["&", "&"], ["y", "__variable_"], ["in", "__R_"], ["REAL", "__O255_"], ["by", "by"], ["XREAL_0", "__label_"], [":", ":"], ["def", "def"], ["1", "__number_"], [";", ";"]], [["A4", "__label_"], [":", ":"], ["z", "__variable_"], ["in", "__R_"], ["REAL", "__O255_"], ["by", "by"], ["XREAL_0", "__label_"], [":", ":"], ["def", "def"], ["1", "__number_"], [";", ";"]], [["per", "per"], ["cases", "cases"], ["by", "by"], ["A3", "__label_"], [",", ","], ["A4", "__label_"], [",", ","], ["NUMBERS", "__label_"], [":", ":"], ["def", "def"], ["1", "__number_"], [",", ","], ["XBOOLE_0", "__label_"], [":", ":"], ["def", "def"], ["3", "__number_"], [";", ";"]], [["suppose", "suppose"], ["that", "that"]], [["A5", "__label_"], [":", ":"], ["x", "__variable_"], ["in", "__R_"], ["REAL+", "__O_"], ["and", "and"]], [["A6", "__label_"], [":", ":"], ["y", "__variable_"], ["in", "__R_"], ["REAL+", "__O_"], ["and", "and"]], [["A7", "__label_"], [":", ":"], ["z", "__variable_"], ["in", "__R_"], ["REAL+", "__O_"], [";", ";"]], [["consider", "consider"], ["y99", "__variable_"], [",", ","], ["z9", "__variable_"], ["being", "being"], ["Element", "__M_"], ["of", "of"], ["REAL+", "__O_"], ["such", "such"], ["that", "that"]], [["A8", "__label_"], [":", ":"], ["y", "__variable_"], ["=", "="], ["y99", "__variable_"], ["and", "and"]], [["A9", "__label_"], [":", ":"], ["z", "__variable_"], ["=", "="], ["z9", "__variable_"], ["and", "and"]], [["A10", "__label_"], [":", ":"], ["y99", "__variable_"], ["<='", "__R_"], ["z9", "__variable_"], ["by", "by"], ["A2", "__label_"], [",", ","], ["A6", "__label_"], [",", ","], ["A7", "__label_"], [",", ","], ["XXREAL_0", "__label_"], [":", ":"], ["def", "def"], ["5", "__number_"], [";", ";"]], [["consider", "consider"], ["x9", "__variable_"], [",", ","], ["y9", "__variable_"], ["being", "being"], ["Element", "__M_"], ["of", "of"], ["REAL+", "__O_"], ["such", "such"], ["that", "that"]], [["A11", "__label_"], [":", ":"], ["x", "__variable_"], ["=", "="], ["x9", "__variable_"], ["and", "and"]], [["A12", "__label_"], [":", ":"], ["y", "__variable_"], ["=", "="], ["y9", "__variable_"], ["&", "&"], ["x9", "__variable_"], ["<='", "__R_"], ["y9", "__variable_"], ["by", "by"], ["A1", "__label_"], [",", ","], ["A5", "__label_"], [",", ","], ["A6", "__label_"], [",", ","], ["XXREAL_0", "__label_"], [":", ":"], ["def", "def"], ["5", "__number_"], [";", ";"]], [["x9", "__variable_"], ["<='", "__R_"], ["z9", "__variable_"], ["by", "by"], ["A12", "__label_"], [",", ","], ["A8", "__label_"], [",", ","], ["A10", "__label_"], [",", ","], ["ARYTM_1", "__label_"], [":", ":"], ["3", "__number_"], [";", ";"]], [["hence", "hence"], ["thesis", "thesis"], ["by", "by"], ["A11", "__label_"], [",", ","], ["A9", "__label_"], [",", ","], ["XXREAL_0", "__label_"], [":", ":"], ["def", "def"], ["5", "__number_"], [";", ";"]], [["end", "end"], [";", ";"]], [["suppose", "suppose"]], [["A13", "__label_"], [":", ":"], ["x", "__variable_"], ["in", "__R_"], ["REAL+", "__O_"], ["&", "&"], ["y", "__variable_"], ["in", "__R_"], ["[:", "__K_"], ["{", "{"], ["0", "__O_"], ["}", "}"], [",", ","], ["REAL+", "__O_"], [":]", "__L_"], [";", ";"]], [["then", "then"]], [["(", "("], ["not", "not"], ["(", "("], ["x", "__variable_"], ["in", "__R_"], ["REAL+", "__O_"], ["&", "&"], ["y", "__variable_"], ["in", "__R_"], ["REAL+", "__O_"], [")", ")"], [")", ")"], ["&", "&"], ["not", "not"], ["(", "("], ["x", "__variable_"], ["in", "__R_"], ["[:", "__K_"], ["{", "{"], ["0", "__O_"], ["}", "}"], [",", ","], ["REAL+", "__O_"], [":]", "__L_"], ["&", "&"], ["y", "__variable_"], ["in", "__R_"], ["[:", "__K_"], ["{", "{"], ["0", "__O_"], ["}", "}"], [",", ","]], [["REAL+", "__O_"], [":]", "__L_"], [")", ")"], ["by", "by"], ["ARYTM_0", "__label_"], [":", ":"], ["5", "__number_"], [",", ","], ["XBOOLE_0", "__label_"], [":", ":"], ["3", "__number_"], [";", ";"]], [["hence", "hence"], ["thesis", "thesis"], ["by", "by"], ["A1", "__label_"], [",", ","], ["A13", "__label_"], [",", ","], ["XXREAL_0", "__label_"], [":", ":"], ["def", "def"], ["5", "__number_"], [";", ";"]], [["end", "end"], [";", ";"]], [["suppose", "suppose"]], [["A14", "__label_"], [":", ":"], ["y", "__variable_"], ["in", "__R_"], ["REAL+", "__O_"], ["&", "&"], ["z", "__variable_"], ["in", "__R_"], ["[:", "__K_"], ["{", "{"], ["0", "__O_"], ["}", "}"], [",", ","], ["REAL+", "__O_"], [":]", "__L_"], [";", ";"]], [["then", "then"]], [["(", "("], ["not", "not"], ["(", "("], ["z", "__variable_"], ["in", "__R_"], ["REAL+", "__O_"], ["&", "&"], ["y", "__variable_"], ["in", "__R_"], ["REAL+", "__O_"], [")", ")"], [")", ")"], ["&", "&"], ["not", "not"], ["(", "("], ["z", "__variable_"], ["in", "__R_"], ["[:", "__K_"], ["{", "{"], ["0", "__O_"], ["}", "}"], [",", ","], ["REAL+", "__O_"], [":]", "__L_"], ["&", "&"], ["y", "__variable_"], ["in", "__R_"], ["[:", "__K_"], ["{", "{"], ["0", "__O_"], ["}", "}"], [",", ","]], [["REAL+", "__O_"], [":]", "__L_"], [")", ")"], ["by", "by"], ["ARYTM_0", "__label_"], [":", ":"], ["5", "__number_"], [",", ","], ["XBOOLE_0", "__label_"], [":", ":"], ["3", "__number_"], [";", ";"]], [["hence", "hence"], ["thesis", "thesis"], ["by", "by"], ["A2", "__label_"], [",", ","], ["A14", "__label_"], [",", ","], ["XXREAL_0", "__label_"], [":", ":"], ["def", "def"], ["5", "__number_"], [";", ";"]], [["end", "end"], [";", ";"]], [["suppose", "suppose"], ["that", "that"]], [["A15", "__label_"], [":", ":"], ["x", "__variable_"], ["in", "__R_"], ["[:", "__K_"], ["{", "{"], ["0", "__O_"], ["}", "}"], [",", ","], ["REAL+", "__O_"], [":]", "__L_"], ["and", "and"]], [["A16", "__label_"], [":", ":"], ["z", "__variable_"], ["in", "__R_"], ["REAL+", "__O_"], [";", ";"]], [["(", "("], ["not", "not"], ["(", "("], ["x", "__variable_"], ["in", "__R_"], ["REAL+", "__O_"], ["&", "&"], ["z", "__variable_"], ["in", "__R_"], ["REAL+", "__O_"], [")", ")"], [")", ")"], ["&", "&"], ["not", "not"], ["(", "("], ["x", "__variable_"], ["in", "__R_"], ["[:", "__K_"], ["{", "{"], ["0", "__O_"], ["}", "}"], [",", ","], ["REAL+", "__O_"], [":]", "__L_"], ["&", "&"], ["z", "__variable_"], ["in", "__R_"], ["[:", "__K_"], ["{", "{"], ["0", "__O_"], ["}", "}"], [",", ","]], [["REAL+", "__O_"], [":]", "__L_"], [")", ")"], ["by", "by"], ["A15", "__label_"], [",", ","], ["A16", "__label_"], [",", ","], ["ARYTM_0", "__label_"], [":", ":"], ["5", "__number_"], [",", ","], ["XBOOLE_0", "__label_"], [":", ":"], ["3", "__number_"], [";", ";"]], [["hence", "hence"], ["thesis", "thesis"], ["by", "by"], ["A16", "__label_"], [",", ","], ["XXREAL_0", "__label_"], [":", ":"], ["def", "def"], ["5", "__number_"], [";", ";"]], [["end", "end"], [";", ";"]], [["suppose", "suppose"], ["that", "that"]], [["A17", "__label_"], [":", ":"], ["x", "__variable_"], ["in", "__R_"], ["[:", "__K_"], ["{", "{"], ["0", "__O_"], ["}", "}"], [",", ","], ["REAL+", "__O_"], [":]", "__L_"], ["and", "and"]], [["A18", "__label_"], [":", ":"], ["y", "__variable_"], ["in", "__R_"], ["[:", "__K_"], ["{", "{"], ["0", "__O_"], ["}", "}"], [",", ","], ["REAL+", "__O_"], [":]", "__L_"], ["and", "and"]], [["A19", "__label_"], [":", ":"], ["z", "__variable_"], ["in", "__R_"], ["[:", "__K_"], ["{", "{"], ["0", "__O_"], ["}", "}"], [",", ","], ["REAL+", "__O_"], [":]", "__L_"], [";", ";"]], [["consider", "consider"], ["y99", "__variable_"], [",", ","], ["z9", "__variable_"], ["being", "being"], ["Element", "__M_"], ["of", "of"], ["REAL+", "__O_"], ["such", "such"], ["that", "that"]], [["A20", "__label_"], [":", ":"], ["y", "__variable_"], ["=", "="], ["[", "["], ["0", "__O_"], [",", ","], ["y99", "__variable_"], ["]", "]"], ["and", "and"]], [["A21", "__label_"], [":", ":"], ["z", "__variable_"], ["=", "="], ["[", "["], ["0", "__O_"], [",", ","], ["z9", "__variable_"], ["]", "]"], ["and", "and"]], [["A22", "__label_"], [":", ":"], ["z9", "__variable_"], ["<='", "__R_"], ["y99", "__variable_"], ["by", "by"], ["A2", "__label_"], [",", ","], ["A18", "__label_"], [",", ","], ["A19", "__label_"], [",", ","], ["XXREAL_0", "__label_"], [":", ":"], ["def", "def"], ["5", "__number_"], [";", ";"]], [["consider", "consider"], ["x9", "__variable_"], [",", ","], ["y9", "__variable_"], ["being", "being"], ["Element", "__M_"], ["of", "of"], ["REAL+", "__O_"], ["such", "such"], ["that", "that"]], [["A23", "__label_"], [":", ":"], ["x", "__variable_"], ["=", "="], ["[", "["], ["0", "__O_"], [",", ","], ["x9", "__variable_"], ["]", "]"], ["and", "and"]], [["A24", "__label_"], [":", ":"], ["y", "__variable_"], ["=", "="], ["[", "["], ["0", "__O_"], [",", ","], ["y9", "__variable_"], ["]", "]"], ["and", "and"]], [["A25", "__label_"], [":", ":"], ["y9", "__variable_"], ["<='", "__R_"], ["x9", "__variable_"], ["by", "by"], ["A1", "__label_"], [",", ","], ["A17", "__label_"], [",", ","], ["A18", "__label_"], [",", ","], ["XXREAL_0", "__label_"], [":", ":"], ["def", "def"], ["5", "__number_"], [";", ";"]], [["y9", "__variable_"], ["=", "="], ["y99", "__variable_"], ["by", "by"], ["A24", "__label_"], [",", ","], ["A20", "__label_"], [",", ","], ["XTUPLE_0", "__label_"], [":", ":"], ["1", "__number_"], [";", ";"]], [["then", "then"], ["z9", "__variable_"], ["<='", "__R_"], ["x9", "__variable_"], ["by", "by"], ["A25", "__label_"], [",", ","], ["A22", "__label_"], [",", ","], ["ARYTM_1", "__label_"], [":", ":"], ["3", "__number_"], [";", ";"]], [["hence", "hence"], ["thesis", "thesis"], ["by", "by"], ["A17", "__label_"], [",", ","], ["A19", "__label_"], [",", ","], ["A23", "__label_"], [",", ","], ["A21", "__label_"], [",", ","], ["XXREAL_0", "__label_"], [":", ":"], ["def", "def"], ["5", "__number_"], [";", ";"]], [["end", "end"], [";", ";"]], [["end", "end"], [";", ";"]], [["theorem", "theorem"]], [["x", "__variable_"], ["<=", "__R_"], ["y", "__variable_"], ["&", "&"], ["x", "__variable_"], ["is", "is"], ["positive", "__V_"], ["implies", "implies"], ["y", "__variable_"], ["is", "is"], ["positive", "__V_"]], [["proof", "proof"]], [["assume", "assume"], ["that", "that"]], [["A1", "__label_"], [":", ":"], ["x", "__variable_"], ["<=", "__R_"], ["y", "__variable_"], ["and", "and"]], [["A2", "__label_"], [":", ":"], ["x", "__variable_"], ["is", "is"], ["positive", "__V_"], [";", ";"]], [["x", "__variable_"], [">", "__R_"], ["0", "__O_"], ["by", "by"], ["A2", "__label_"], [",", ","], ["XXREAL_0", "__label_"], [":", ":"], ["def", "def"], ["6", "__number_"], [";", ";"]], [["then", "then"], ["y", "__variable_"], [">", "__R_"], ["0", "__O_"], ["by", "by"], ["A1", "__label_"], [",", ","], ["Lm2", "__label_"], [";", ";"]], [["hence", "hence"], ["thesis", "thesis"], ["by", "by"], ["XXREAL_0", "__label_"], [":", ":"], ["def", "def"], ["6", "__number_"], [";", ";"]], [["end", "end"], [";", ";"]], [["theorem", "theorem"]], [["x", "__variable_"], ["<=", "__R_"], ["y", "__variable_"], ["&", "&"], ["y", "__variable_"], ["is", "is"], ["negative", "__V_"], ["implies", "implies"], ["x", "__variable_"], ["is", "is"], ["negative", "__V_"]], [["proof", "proof"]], [["assume", "assume"], ["that", "that"]], [["A1", "__label_"], [":", ":"], ["x", "__variable_"], ["<=", "__R_"], ["y", "__variable_"], ["and", "and"]], [["A2", "__label_"], [":", ":"], ["y", "__variable_"], ["is", "is"], ["negative", "__V_"], [";", ";"]], [["y", "__variable_"], ["<", "__R_"], ["0", "__O_"], ["by", "by"], ["A2", "__label_"], [",", ","], ["XXREAL_0", "__label_"], [":", ":"], ["def", "def"], ["7", "__number_"], [";", ";"]], [["then", "then"], ["x", "__variable_"], ["<", "__R_"], ["0", "__O_"], ["by", "by"], ["A1", "__label_"], [",", ","], ["Lm2", "__label_"], [";", ";"]], [["hence", "hence"], ["thesis", "thesis"], ["by", "by"], ["XXREAL_0", "__label_"], [":", ":"], ["def", "def"], ["7", "__number_"], [";", ";"]], [["end", "end"], [";", ";"]], [["theorem", "theorem"]], [["x", "__variable_"], ["<=", "__R_"], ["y", "__variable_"], ["&", "&"], ["x", "__variable_"], ["is", "is"], ["non", "non"], ["negative", "__V_"], ["implies", "implies"], ["y", "__variable_"], ["is", "is"], ["non", "non"], ["negative", "__V_"]], [["proof", "proof"]], [["assume", "assume"], ["that", "that"]], [["A1", "__label_"], [":", ":"], ["x", "__variable_"], ["<=", "__R_"], ["y", "__variable_"], ["and", "and"]], [["A2", "__label_"], [":", ":"], ["x", "__variable_"], ["is", "is"], ["non", "non"], ["negative", "__V_"], ["and", "and"]], [["A3", "__label_"], [":", ":"], ["y", "__variable_"], ["is", "is"], ["negative", "__V_"], [";", ";"]], [["y", "__variable_"], ["<", "__R_"], ["0", "__O_"], ["by", "by"], ["A3", "__label_"], [",", ","], ["XXREAL_0", "__label_"], [":", ":"], ["def", "def"], ["7", "__number_"], [";", ";"]], [["then", "then"], ["x", "__variable_"], ["<", "__R_"], ["0", "__O_"], ["by", "by"], ["A1", "__label_"], [",", ","], ["Lm2", "__label_"], [";", ";"]], [["hence", "hence"], ["thesis", "thesis"], ["by", "by"], ["A2", "__label_"], [",", ","], ["XXREAL_0", "__label_"], [":", ":"], ["def", "def"], ["7", "__number_"], [";", ";"]], [["end", "end"], [";", ";"]], [["theorem", "theorem"]], [["x", "__variable_"], ["<=", "__R_"], ["y", "__variable_"], ["&", "&"], ["y", "__variable_"], ["is", "is"], ["non", "non"], ["positive", "__V_"], ["implies", "implies"], ["x", "__variable_"], ["is", "is"], ["non", "non"], ["positive", "__V_"]], [["proof", "proof"]], [["assume", "assume"], ["that", "that"]], [["A1", "__label_"], [":", ":"], ["x", "__variable_"], ["<=", "__R_"], ["y", "__variable_"], ["and", "and"]], [["A2", "__label_"], [":", ":"], ["y", "__variable_"], ["is", "is"], ["non", "non"], ["positive", "__V_"], ["and", "and"]], [["A3", "__label_"], [":", ":"], ["x", "__variable_"], ["is", "is"], ["positive", "__V_"], [";", ";"]], [["x", "__variable_"], [">", "__R_"], ["0", "__O_"], ["by", "by"], ["A3", "__label_"], [",", ","], ["XXREAL_0", "__label_"], [":", ":"], ["def", "def"], ["6", "__number_"], [";", ";"]], [["then", "then"], ["y", "__variable_"], [">", "__R_"], ["0", "__O_"], ["by", "by"], ["A1", "__label_"], [",", ","], ["Lm2", "__label_"], [";", ";"]], [["hence", "hence"], ["thesis", "thesis"], ["by", "by"], ["A2", "__label_"], [",", ","], ["XXREAL_0", "__label_"], [":", ":"], ["def", "def"], ["6", "__number_"], [";", ";"]], [["end", "end"], [";", ";"]], [["theorem", "theorem"]], [["x", "__variable_"], ["<=", "__R_"], ["y", "__variable_"], ["&", "&"], ["y", "__variable_"], ["is", "is"], ["non", "non"], ["zero", "__V_"], ["&", "&"], ["x", "__variable_"], ["is", "is"], ["non", "non"], ["negative", "__V_"], ["implies", "implies"], ["y", "__variable_"], ["is", "is"], ["positive", "__V_"]], [["proof", "proof"]], [["assume", "assume"], ["that", "that"]], [["A1", "__label_"], [":", ":"], ["x", "__variable_"], ["<=", "__R_"], ["y", "__variable_"], ["and", "and"]], [["A2", "__label_"], [":", ":"], ["y", "__variable_"], ["is", "is"], ["non", "non"], ["zero", "__V_"], ["and", "and"]], [["A3", "__label_"], [":", ":"], ["x", "__variable_"], ["is", "is"], ["non", "non"], ["negative", "__V_"], ["and", "and"]], [["A4", "__label_"], [":", ":"], ["y", "__variable_"], ["is", "is"], ["non", "non"], ["positive", "__V_"], [";", ";"]], [["y", "__variable_"], ["<=", "__R_"], ["0", "__O_"], ["by", "by"], ["A4", "__label_"], [",", ","], ["XXREAL_0", "__label_"], [":", ":"], ["def", "def"], ["6", "__number_"], [";", ";"]], [["then", "then"]], [["A5", "__label_"], [":", ":"], ["y", "__variable_"], ["<", "__R_"], ["0", "__O_"], ["by", "by"], ["A2", "__label_"], [",", ","], ["Lm1", "__label_"], [";", ";"]], [["x", "__variable_"], [">=", "__R_"], ["0", "__O_"], ["by", "by"], ["A3", "__label_"], [",", ","], ["XXREAL_0", "__label_"], [":", ":"], ["def", "def"], ["7", "__number_"], [";", ";"]], [["hence", "hence"], ["thesis", "thesis"], ["by", "by"], ["A1", "__label_"], [",", ","], ["A5", "__label_"], [",", ","], ["Lm2", "__label_"], [";", ";"]], [["end", "end"], [";", ";"]], [["theorem", "theorem"]], [["x", "__variable_"], ["<=", "__R_"], ["y", "__variable_"], ["&", "&"], ["x", "__variable_"], ["is", "is"], ["non", "non"], ["zero", "__V_"], ["&", "&"], ["y", "__variable_"], ["is", "is"], ["non", "non"], ["positive", "__V_"], ["implies", "implies"], ["x", "__variable_"], ["is", "is"], ["negative", "__V_"]], [["proof", "proof"]], [["assume", "assume"], ["that", "that"]], [["A1", "__label_"], [":", ":"], ["x", "__variable_"], ["<=", "__R_"], ["y", "__variable_"], ["and", "and"]], [["A2", "__label_"], [":", ":"], ["x", "__variable_"], ["is", "is"], ["non", "non"], ["zero", "__V_"], ["and", "and"]], [["A3", "__label_"], [":", ":"], ["y", "__variable_"], ["is", "is"], ["non", "non"], ["positive", "__V_"], ["and", "and"]], [["A4", "__label_"], [":", ":"], ["x", "__variable_"], ["is", "is"], ["non", "non"], ["negative", "__V_"], [";", ";"]], [["x", "__variable_"], [">=", "__R_"], ["0", "__O_"], ["by", "by"], ["A4", "__label_"], [",", ","], ["XXREAL_0", "__label_"], [":", ":"], ["def", "def"], ["7", "__number_"], [";", ";"]], [["then", "then"]], [["A5", "__label_"], [":", ":"], ["x", "__variable_"], [">", "__R_"], ["0", "__O_"], ["by", "by"], ["A2", "__label_"], [",", ","], ["Lm1", "__label_"], [";", ";"]], [["y", "__variable_"], ["<=", "__R_"], ["0", "__O_"], ["by", "by"], ["A3", "__label_"], [",", ","], ["XXREAL_0", "__label_"], [":", ":"], ["def", "def"], ["6", "__number_"], [";", ";"]], [["hence", "hence"], ["thesis", "thesis"], ["by", "by"], ["A1", "__label_"], [",", ","], ["A5", "__label_"], [",", ","], ["Lm2", "__label_"], [";", ";"]], [["end", "end"], [";", ";"]], [["theorem", "theorem"]], [["not", "not"], ["x", "__variable_"], ["<=", "__R_"], ["y", "__variable_"], ["&", "&"], ["x", "__variable_"], ["is", "is"], ["non", "non"], ["positive", "__V_"], ["implies", "implies"], ["y", "__variable_"], ["is", "is"], ["negative", "__V_"]], [["proof", "proof"]], [["assume", "assume"], ["that", "that"]], [["A1", "__label_"], [":", ":"], ["x", "__variable_"], [">", "__R_"], ["y", "__variable_"], ["and", "and"]], [["A2", "__label_"], [":", ":"], ["x", "__variable_"], ["is", "is"], ["non", "non"], ["positive", "__V_"], ["&", "&"], ["y", "__variable_"], ["is", "is"], ["non", "non"], ["negative", "__V_"], [";", ";"]], [["x", "__variable_"], ["<=", "__R_"], ["0", "__O_"], ["&", "&"], ["y", "__variable_"], [">=", "__R_"], ["0", "__O_"], ["by", "by"], ["A2", "__label_"], [",", ","], ["XXREAL_0", "__label_"], [":", ":"], ["def", "def"], ["6", "__number_"], [",", ","], ["def", "def"], ["7", "__number_"], [";", ";"]], [["hence", "hence"], ["thesis", "thesis"], ["by", "by"], ["A1", "__label_"], [",", ","], ["Lm2", "__label_"], [";", ";"]], [["end", "end"], [";", ";"]], [["theorem", "theorem"]], [["not", "not"], ["x", "__variable_"], ["<=", "__R_"], ["y", "__variable_"], ["&", "&"], ["y", "__variable_"], ["is", "is"], ["non", "non"], ["negative", "__V_"], ["implies", "implies"], ["x", "__variable_"], ["is", "is"], ["positive", "__V_"]], [["proof", "proof"]], [["assume", "assume"], ["that", "that"]], [["A1", "__label_"], [":", ":"], ["x", "__variable_"], [">", "__R_"], ["y", "__variable_"], ["and", "and"]], [["A2", "__label_"], [":", ":"], ["y", "__variable_"], ["is", "is"], ["non", "non"], ["negative", "__V_"], ["&", "&"], ["x", "__variable_"], ["is", "is"], ["non", "non"], ["positive", "__V_"], [";", ";"]], [["x", "__variable_"], ["<=", "__R_"], ["0", "__O_"], ["&", "&"], ["y", "__variable_"], [">=", "__R_"], ["0", "__O_"], ["by", "by"], ["A2", "__label_"], [",", ","], ["XXREAL_0", "__label_"], [":", ":"], ["def", "def"], ["6", "__number_"], [",", ","], ["def", "def"], ["7", "__number_"], [";", ";"]], [["hence", "hence"], ["thesis", "thesis"], ["by", "by"], ["A1", "__label_"], [",", ","], ["Lm2", "__label_"], [";", ";"]], [["end", "end"], [";", ";"]]]}